braian/__init__.py
braian/animal_brain.py
braian/animal_group.py
braian/brain_data.py
braian/brain_slice.py
braian/config.py
braian/deflector.py
braian/experiment.py
braian/ontology.py
braian/plot/__init__.py
braian/plot/generic.py
braian/plot/heatmap.py
braian/plot/ontology.py
braian/plot/pls.py
braian/plot/xmastree.py
braian/resources/CCFv3_summary_structures.csv
braian/resources/CCFv3_summary_structures.csv.license
braian/sliced_brain.py
braian/stats/__init__.py
braian/stats/metrics.py
braian/stats/pls.py
braian/utils.py
braian/visit_dict.py
braian-1.0.5.dist-info/LICENSES/CC-BY-4.0.txt
braian-1.0.5.dist-info/LICENSES/CC-BY-NC-ND-4.0.txt
braian-1.0.5.dist-info/LICENSES/CC0-1.0.txt
braian-1.0.5.dist-info/LICENSES/ISC.txt
braian-1.0.5.dist-info/LICENSES/LGPL-3.0-or-later.txt
braian-1.0.5.dist-info/LICENSES/MIT.txt
braian-1.0.5.dist-info/METADATA
braian-1.0.5.dist-info/WHEEL
braian-1.0.5.dist-info/RECORD
