Metadata-Version: 2.3
Name: braian
Version: 1.0.5
Summary: A python library for easy navigation, visualisation, and analysis of whole-brain quantification data.
License: LGPL-3.0-or-later
Keywords: data-analysis,library,neuroscience,visualisation,visualization,whole-brain
Author: Carlo Castoldi
Author-email: carlo.castoldi@outlook.com
Requires-Python: >=3.11,<3.14
Classifier: License :: OSI Approved :: GNU Lesser General Public License v3 or later (LGPLv3+)
Classifier: Programming Language :: Python :: 3
Classifier: Programming Language :: Python :: 3.11
Classifier: Programming Language :: Python :: 3.12
Classifier: Programming Language :: Python :: 3.13
Requires-Dist: beautifulsoup4 (>=4.12.3,<=5.0.0)
Requires-Dist: brainglobe-heatmap (>=0.5.4,<1.0.0)
Requires-Dist: kaleido (==0.2.1)
Requires-Dist: numpy (>=2.0.2,<2.2.0)
Requires-Dist: pandas (>=2.2.3,<3.0.0)
Requires-Dist: plotly (>=5.24.1,<6.0.0)
Requires-Dist: python-igraph (>=0.11.8,<1.0.0)
Requires-Dist: pywin32 (>=306) ; sys_platform == "win32"
Requires-Dist: pyyaml (>=6.0.2,<7.0.0)
Requires-Dist: scipy (>=1.15.1,<2.0.0)
Requires-Dist: tables (>=3.9.2,<4.0.0)
Requires-Dist: urllib3 (>=1.26.16,<2.0.0)
